kody_clientsdk_python/__init__.py
kody_clientsdk_python/common/__init__.py
kody_clientsdk_python/common/enums_pb2.py
kody_clientsdk_python/common/enums_pb2_grpc.py
kody_clientsdk_python/ecom/__init__.py
kody_clientsdk_python/ecom/v1/__init__.py
kody_clientsdk_python/ecom/v1/ecom_pb2.py
kody_clientsdk_python/ecom/v1/ecom_pb2_grpc.py
kody_clientsdk_python/errors/__init__.py
kody_clientsdk_python/errors/error_pb2.py
kody_clientsdk_python/errors/error_pb2_grpc.py
kody_clientsdk_python/ordering/__init__.py
kody_clientsdk_python/ordering/v1/__init__.py
kody_clientsdk_python/ordering/v1/inventory_pb2.py
kody_clientsdk_python/ordering/v1/inventory_pb2_grpc.py
kody_clientsdk_python/ordering/v1/order_pb2.py
kody_clientsdk_python/ordering/v1/order_pb2_grpc.py
kody_clientsdk_python/pay/__init__.py
kody_clientsdk_python/pay/v1/__init__.py
kody_clientsdk_python/pay/v1/pay_pb2.py
kody_clientsdk_python/pay/v1/pay_pb2_grpc.py
kody_clientsdk_python/pay/v1/token_pb2.py
kody_clientsdk_python/pay/v1/token_pb2_grpc.py
kody_clientsdk_python/payattable/__init__.py
kody_clientsdk_python/payattable/v1/__init__.py
kody_clientsdk_python/payattable/v1/pay_at_table_pb2.py
kody_clientsdk_python/payattable/v1/pay_at_table_pb2_grpc.py
kody_clientsdk_python/poc/__init__.py
kody_clientsdk_python/poc/poc_pb2.py
kody_clientsdk_python/poc/poc_pb2_grpc.py
kody_clientsdk_python/preauth/__init__.py
kody_clientsdk_python/preauth/v1/__init__.py
kody_clientsdk_python/preauth/v1/preauth_pb2.py
kody_clientsdk_python/preauth/v1/preauth_pb2_grpc.py
kody_clientsdk_python/utils/__init__.py
kody_clientsdk_python/utils/v1/__init__.py
kody_clientsdk_python/utils/v1/logging_pb2.py
kody_clientsdk_python/utils/v1/logging_pb2_grpc.py
kody_clientsdk_python-1.7.33.dist-info/METADATA
kody_clientsdk_python-1.7.33.dist-info/WHEEL
kody_clientsdk_python-1.7.33.dist-info/top_level.txt
kody_clientsdk_python-1.7.33.dist-info/RECORD
