Metadata-Version: 2.4
Name: kody_clientsdk_python
Version: 1.7.33
Summary: Kody API client
Home-page: https://github.com/KodyPay/kody-clientsdk-python
Author: Kody Tech Team
Author-email: tech@kody.com
License: MIT
Requires-Dist: grpcio==1.66.1
Requires-Dist: protobuf==5.27.2
Dynamic: author
Dynamic: author-email
Dynamic: description
Dynamic: home-page
Dynamic: license
Dynamic: requires-dist
Dynamic: summary
